{"countryCode":"MK","branches":[{"bic":"USINMK21","bank":"ARCELORMITTAL SKOPJE (CRM)","branch":"","city":"SKOPJE","country":"MK","address":""},{"bic":"BDBKMK21","bank":"BRO-DEAL, INC","branch":"","city":"SKOPJE","country":"MK","address":""},{"bic":"POBRMK21","bank":"BROKER HOUSE POSTEL-BROKER A.D","branch":"","city":"SKOPJE","country":"MK","address":""},{"bic":"KBBRMK21","bank":"BROKERAGE HOUSE KB BROKER INC.SKOPJE","branch":"","city":"SKOPJE","country":"MK","address":""},{"bic":"MIBRMK21","bank":"BROKERAGE HOUSE MAKOS-INVEST BROKER INC","branch":"","city":"SKOPJE","country":"MK","address":""},{"bic":"SBSBMK21","bank":"BROKER-SB A.D. SKOPJE BROKERAGE HOUSE OF STOPANSKA BANKA AD SKOPJE","branch":"","city":"SKOPJE","country":"MK","address":""},{"bic":"INPBMK21","bank":"CAPITAL BANK AD","branch":"","city":"SKOPJE","country":"MK","address":""},{"bic":"CECBMK22","bank":"CENTRAL COOPERATIVE BANK AD SKOPJE","branch":"","city":"SKOPJE","country":"MK","address":""},{"bic":"CDHVMK21","bank":"CENTRAL SECURITIES DEPOSITORY JSC","branch":"","city":"SKOPJE","country":"MK","address":""},{"bic":"KIBSMK21","bank":"CLEARING HOUSE INTERBANK CLEARING SYSTEMS","branch":"","city":"SKOPJE","country":"MK","address":""},{"bic":"ESWBMK22","bank":"EUROSTANDARD BANK AD","branch":"","city":"SKOPJE","country":"MK","address":""},{"bic":"FLAMMK21","bank":"FERSPED - BROKER AD","branch":"","city":"SKOPJE","country":"MK","address":""},{"bic":"EXPCMK22","bank":"HALKBANK AD SKOPJE","branch":"","city":"SKOPJE","country":"MK","address":""},{"bic":"HIFDMK21","bank":"HEALTH INSURANCE FUND OF MACEDONIA","branch":"","city":"SKOPJE","country":"MK","address":""},{"bic":"KAPBMK22","bank":"KAPITAL BANKA AD SKOPJE","branch":"","city":"SKOPJE","country":"MK","address":""},{"bic":"KOBSMK2XBTB","bank":"KOMERCIJALNA BANKA AD SKOPJE","branch":"","city":"BITOLA","country":"MK","address":""},{"bic":"KOBSMK2XGVB","bank":"KOMERCIJALNA BANKA AD SKOPJE","branch":"","city":"GOSTIVAR","country":"MK","address":""},{"bic":"KOBSMK2XKVB","bank":"KOMERCIJALNA BANKA AD SKOPJE","branch":"","city":"KAVADARCI","country":"MK","address":""},{"bic":"KOBSMK2XKOB","bank":"KOMERCIJALNA BANKA AD SKOPJE","branch":"","city":"KOCANI","country":"MK","address":""},{"bic":"KOBSMK2XKUB","bank":"KOMERCIJALNA BANKA AD SKOPJE","branch":"","city":"KUMANOVO","country":"MK","address":""},{"bic":"KOBSMK2XOHB","bank":"KOMERCIJALNA BANKA AD SKOPJE","branch":"","city":"OHRID","country":"MK","address":""},{"bic":"KOBSMK2XPRB","bank":"KOMERCIJALNA BANKA AD SKOPJE","branch":"","city":"PRILEP","country":"MK","address":""},{"bic":"KOBSMK2X","bank":"KOMERCIJALNA BANKA AD SKOPJE","branch":"","city":"SKOPJE","country":"MK","address":""},{"bic":"KOBSMK2XSTB","bank":"KOMERCIJALNA BANKA AD SKOPJE","branch":"","city":"STIP","country":"MK","address":""},{"bic":"KOBSMK2XSRB","bank":"KOMERCIJALNA BANKA AD SKOPJE","branch":"","city":"STRUMICA","country":"MK","address":""},{"bic":"KOBSMK2XTEB","bank":"KOMERCIJALNA BANKA AD SKOPJE","branch":"","city":"TETOVO","country":"MK","address":""},{"bic":"KOBSMK2XVEB","bank":"KOMERCIJALNA BANKA AD SKOPJE","branch":"","city":"VELES","country":"MK","address":""},{"bic":"MBDPMK22","bank":"MACEDONIAN BANK FOR DEVELOPMENT PROMOTION","branch":"","city":"SKOPJE","country":"MK","address":""},{"bic":"XMAEMK21","bank":"MACEDONIAN STOCK EXCHANGE AD","branch":"","city":"SKOPJE","country":"MK","address":""},{"bic":"MBBRMK21","bank":"MAK BROKER AD","branch":"","city":"SKOPJE","country":"MK","address":""},{"bic":"PPHVMK21","bank":"MONEY MARKET AND SHORT-TERM SECURITIES OF THE REP. OF MACEDONIA","branch":"","city":"SKOPJE","country":"MK","address":""},{"bic":"NBRMMK2A","bank":"NATIONAL BANK OF THE REPUBLIC OF MACEDONIA","branch":"","city":"SKOPJE","country":"MK","address":""},{"bic":"NBRMMK2X","bank":"NATIONAL BANK OF THE REPUBLIC OF MACEDONIA","branch":"","city":"SKOPJE","country":"MK","address":""},{"bic":"NPKMMK21","bank":"NATIONAL PAYMENT CARD AD","branch":"","city":"SKOPJE","country":"MK","address":""},{"bic":"TUTNMK22","bank":"NLB BANKA AD SKOPJE","branch":"","city":"SKOPJE","country":"MK","address":""},{"bic":"OHRDMK22","bank":"OHRIDSKA BANKA A.D. SKOPJE","branch":"","city":"SKOPJE","country":"MK","address":""},{"bic":"PELAMK21","bank":"PELAGONISKA BANKA AD","branch":"","city":"PRILEP","country":"MK","address":""},{"bic":"PRBUMK22","bank":"PROCREDIT BANK, MACEDONIA (FORMERLY PRO BUSINESS BANK A.D. SKOPJE)","branch":"","city":"SKOPJE","country":"MK","address":""},{"bic":"SKBRMK21","bank":"SAKSES BROKERS INC","branch":"","city":"SKOPJE","country":"MK","address":""},{"bic":"KRSKMK2X","bank":"SILK ROAD BANK AD SKOPJE","branch":"","city":"SKOPJE","country":"MK","address":""},{"bic":"INSBMK22","bank":"SPARKASSE BANK MAKEDONIJA AD SKOPJE","branch":"","city":"SKOPJE","country":"MK","address":""},{"bic":"STOBMK2X","bank":"STOPANSKA BANKA A.D.","branch":"","city":"SKOPJE","country":"MK","address":""},{"bic":"STBBMK22","bank":"STOPANSKA BANKA AD BITOLA","branch":"","city":"BITOLA","country":"MK","address":""},{"bic":"BATSMK21","bank":"TDR SKOPJE D.O.O.E.L.","branch":"","city":"SKOPJE","country":"MK","address":""},{"bic":"TTXBMK2X","bank":"TTK BANKA AD SKOPJE","branch":"","city":"SKOPJE","country":"MK","address":""},{"bic":"UIBMMK22","bank":"UNIVERSAL INVESTMENT BANK AD SKOPJE (UNIBANK)","branch":"","city":"SKOPJE","country":"MK","address":""},{"bic":"KMBPMK21","bank":"ZAVOD ZA PLATEN PROMET","branch":"","city":"SKOPJE","country":"MK","address":""},{"bic":"ZEMBMK21","bank":"ZEMJODELSKA BANKA A.D.","branch":"","city":"SKOPJE","country":"MK","address":""}]}