{"countryCode":"PR","banks":[{"name":"ACESCO CARIBE, MFG.","slug":"acesco-caribe-mfg-","primaryBic":"ACAIPR21"},{"name":"ACTIVO INTERNATIONAL BANK","slug":"activo-international-bank","primaryBic":"ACTTPRSJ"},{"name":"ANDCAPITAL BANK INTERNATIONAL CORP","slug":"andcapital-bank-international-corp","primaryBic":"ACBIPR22"},{"name":"ARCA INTERNATIONAL BANK, INC.","slug":"arca-international-bank-inc-","primaryBic":"ARNRPRSJ"},{"name":"BANCO POPULAR DE PUERTO RICO","slug":"banco-popular-de-puerto-rico","primaryBic":"BPPRPRSB"},{"name":"BANCO SAN JUAN INTERNACIONAL INC","slug":"banco-san-juan-internacional-inc","primaryBic":"BSJIPRSJ"},{"name":"BANCO SANTANDER PUERTO RICO","slug":"banco-santander-puerto-rico","primaryBic":"BSCHPRP1SOB"},{"name":"BANCOLOMBIA PUERTO RICO INTERNACIONAL INC.","slug":"bancolombia-puerto-rico-internacional-inc-","primaryBic":"CFSUPRSJ"},{"name":"BANCREDITO INTERNATIONAL BANK CORP","slug":"bancredito-international-bank-corp","primaryBic":"BIBCPRSJ"},{"name":"BANPLUS INTERNATIONAL BANK, INC.","slug":"banplus-international-bank-inc-","primaryBic":"BIPNPRSJ"},{"name":"BNC INTERNATIONAL BANKING CORPORATION","slug":"bnc-international-banking-corporation","primaryBic":"CIBPPRSJ"},{"name":"CARIBE INTERNATIONAL BANK, CORP.","slug":"caribe-international-bank-corp-","primaryBic":"CBNTPRSJ"},{"name":"CITIBANK, NA PUERTO RICO","slug":"citibank-na-puerto-rico","primaryBic":"CITIPRSJ"},{"name":"COOPERATIVA DE AHORRO Y CREDITO SOL","slug":"cooperativa-de-ahorro-y-credito-sol","primaryBic":"CPELPRSJ"},{"name":"ELITE INTERNATIONAL BANK","slug":"elite-international-bank","primaryBic":"ELIRPRSJ"},{"name":"EURO PACIFIC INTL. BANK, INC.","slug":"euro-pacific-intl-bank-inc-","primaryBic":"EUPNPRSJ"},{"name":"FACEBANK INTERNATIONAL CORPORATION","slug":"facebank-international-corporation","primaryBic":"FILCPR22"},{"name":"FIRSTBANK PUERTO RICO","slug":"firstbank-puerto-rico","primaryBic":"FBPRPRSJ"},{"name":"GBTD CAPITAL ADVISERS LLC","slug":"gbtd-capital-advisers-llc","primaryBic":"GBDCPR21"},{"name":"GBTD GROUP-PUERTO RICO","slug":"gbtd-group-puerto-rico","primaryBic":"GBPRPR21"},{"name":"GBTD SAVINGS AND LOAN GROUP-PUERTO RICO","slug":"gbtd-savings-and-loan-group-puerto-rico","primaryBic":"GBLGPR21"},{"name":"ITALBANK INTERNATIONAL, INC","slug":"italbank-international-inc","primaryBic":"IBIIPRSJ"},{"name":"NODUS INTERNATIONAL BANK","slug":"nodus-international-bank","primaryBic":"NDBKPRSJ"},{"name":"ORIENTAL BANK","slug":"oriental-bank","primaryBic":"OBPRPRSJ"},{"name":"PONCE FEDERAL BANK","slug":"ponce-federal-bank","primaryBic":"PFEBPR21"},{"name":"SCOTIABANK DE PUERTO RICO","slug":"scotiabank-de-puerto-rico","primaryBic":"NOSCPR22"},{"name":"STATETRUST INTERNATIONAL BANK AND TRUST, LLC","slug":"statetrust-international-bank-and-trust-llc","primaryBic":"STULPRSJ"},{"name":"STERN INTERNATIONAL BANK LLC","slug":"stern-international-bank-llc","primaryBic":"SIECPRSJ"},{"name":"VESTIN BANK INTERNATIONAL LLC","slug":"vestin-bank-international-llc","primaryBic":"VEILPRSJ"}],"bankDetails":{"acesco-caribe-mfg-":{"bank":"ACESCO CARIBE, MFG.","country":"PR","branches":[{"bic":"ACAIPR21","bank":"ACESCO CARIBE, MFG.","branch":"","city":"CATANO","country":"PR","address":""}]},"activo-international-bank":{"bank":"ACTIVO INTERNATIONAL BANK","country":"PR","branches":[{"bic":"ACTTPRSJ","bank":"ACTIVO INTERNATIONAL BANK","branch":"","city":"SAN JUAN","country":"PR","address":""}]},"andcapital-bank-international-corp":{"bank":"ANDCAPITAL BANK INTERNATIONAL CORP","country":"PR","branches":[{"bic":"ACBIPR22","bank":"ANDCAPITAL BANK INTERNATIONAL CORP","branch":"","city":"HATO REY","country":"PR","address":""}]},"arca-international-bank-inc-":{"bank":"ARCA INTERNATIONAL BANK, INC.","country":"PR","branches":[{"bic":"ARNRPRSJ","bank":"ARCA INTERNATIONAL BANK, INC.","branch":"","city":"SAN JUAN","country":"PR","address":""}]},"banco-popular-de-puerto-rico":{"bank":"BANCO POPULAR DE PUERTO RICO","country":"PR","branches":[{"bic":"BPPRPRSB","bank":"BANCO POPULAR DE PUERTO RICO","branch":"","city":"SAN JUAN","country":"PR","address":""},{"bic":"BPPRPRSX","bank":"BANCO POPULAR DE PUERTO RICO","branch":"","city":"SAN JUAN","country":"PR","address":""}]},"banco-san-juan-internacional-inc":{"bank":"BANCO SAN JUAN INTERNACIONAL INC","country":"PR","branches":[{"bic":"BSJIPRSJ","bank":"BANCO SAN JUAN INTERNACIONAL INC","branch":"","city":"GUAYNABO","country":"PR","address":""}]},"banco-santander-puerto-rico":{"bank":"BANCO SANTANDER PUERTO RICO","country":"PR","branches":[{"bic":"BSCHPRP1SOB","bank":"BANCO SANTANDER PUERTO RICO","branch":"","city":"SAN JUAN","country":"PR","address":""},{"bic":"BSCHPRSX","bank":"BANCO SANTANDER PUERTO RICO","branch":"","city":"SAN JUAN","country":"PR","address":""},{"bic":"BSCHPRSXSOV","bank":"BANCO SANTANDER PUERTO RICO","branch":"","city":"SAN JUAN","country":"PR","address":""}]},"bancolombia-puerto-rico-internacional-inc-":{"bank":"BANCOLOMBIA PUERTO RICO INTERNACIONAL INC.","country":"PR","branches":[{"bic":"CFSUPRSJ","bank":"BANCOLOMBIA PUERTO RICO INTERNACIONAL INC.","branch":"","city":"SAN JUAN","country":"PR","address":""}]},"bancredito-international-bank-corp":{"bank":"BANCREDITO INTERNATIONAL BANK CORP","country":"PR","branches":[{"bic":"BIBCPRSJ","bank":"BANCREDITO INTERNATIONAL BANK CORP","branch":"","city":"SAN JUAN","country":"PR","address":""}]},"banplus-international-bank-inc-":{"bank":"BANPLUS INTERNATIONAL BANK, INC.","country":"PR","branches":[{"bic":"BIPNPRSJ","bank":"BANPLUS INTERNATIONAL BANK, INC.","branch":"","city":"SAN JUAN","country":"PR","address":""}]},"bnc-international-banking-corporation":{"bank":"BNC INTERNATIONAL BANKING CORPORATION","country":"PR","branches":[{"bic":"CIBPPRSJ","bank":"BNC INTERNATIONAL BANKING CORPORATION","branch":"","city":"SAN JUAN","country":"PR","address":""}]},"caribe-international-bank-corp-":{"bank":"CARIBE INTERNATIONAL BANK, CORP.","country":"PR","branches":[{"bic":"CBNTPRSJ","bank":"CARIBE INTERNATIONAL BANK, CORP.","branch":"","city":"SAN JUAN","country":"PR","address":""}]},"citibank-na-puerto-rico":{"bank":"CITIBANK, NA PUERTO RICO","country":"PR","branches":[{"bic":"CITIPRSJ","bank":"CITIBANK, NA PUERTO RICO","branch":"","city":"SAN JUAN","country":"PR","address":""}]},"cooperativa-de-ahorro-y-credito-sol":{"bank":"COOPERATIVA DE AHORRO Y CREDITO SOL","country":"PR","branches":[{"bic":"CPELPRSJ","bank":"COOPERATIVA DE AHORRO Y CREDITO SOL","branch":"","city":"SAN JUAN","country":"PR","address":""}]},"elite-international-bank":{"bank":"ELITE INTERNATIONAL BANK","country":"PR","branches":[{"bic":"ELIRPRSJ","bank":"ELITE INTERNATIONAL BANK","branch":"","city":"SAN JUAN","country":"PR","address":""}]},"euro-pacific-intl-bank-inc-":{"bank":"EURO PACIFIC INTL. BANK, INC.","country":"PR","branches":[{"bic":"EUPNPRSJ","bank":"EURO PACIFIC INTL. BANK, INC.","branch":"","city":"SAN JUAN","country":"PR","address":""}]},"facebank-international-corporation":{"bank":"FACEBANK INTERNATIONAL CORPORATION","country":"PR","branches":[{"bic":"FILCPR22","bank":"FACEBANK INTERNATIONAL CORPORATION","branch":"","city":"GUAYNABO","country":"PR","address":""}]},"firstbank-puerto-rico":{"bank":"FIRSTBANK PUERTO RICO","country":"PR","branches":[{"bic":"FBPRPRSJ","bank":"FIRSTBANK PUERTO RICO","branch":"","city":"SANTURCE","country":"PR","address":""}]},"gbtd-capital-advisers-llc":{"bank":"GBTD CAPITAL ADVISERS LLC","country":"PR","branches":[{"bic":"GBDCPR21","bank":"GBTD CAPITAL ADVISERS LLC","branch":"","city":"GUAYNABO","country":"PR","address":""}]},"gbtd-group-puerto-rico":{"bank":"GBTD GROUP-PUERTO RICO","country":"PR","branches":[{"bic":"GBPRPR21","bank":"GBTD GROUP-PUERTO RICO","branch":"","city":"GUAYNABO","country":"PR","address":""}]},"gbtd-savings-and-loan-group-puerto-rico":{"bank":"GBTD SAVINGS AND LOAN GROUP-PUERTO RICO","country":"PR","branches":[{"bic":"GBLGPR21","bank":"GBTD SAVINGS AND LOAN GROUP-PUERTO RICO","branch":"","city":"GUAYNABO","country":"PR","address":""}]},"italbank-international-inc":{"bank":"ITALBANK INTERNATIONAL, INC","country":"PR","branches":[{"bic":"IBIIPRSJ","bank":"ITALBANK INTERNATIONAL, INC","branch":"","city":"SAN JUAN","country":"PR","address":""}]},"nodus-international-bank":{"bank":"NODUS INTERNATIONAL BANK","country":"PR","branches":[{"bic":"NDBKPRSJ","bank":"NODUS INTERNATIONAL BANK","branch":"","city":"SAN JUAN","country":"PR","address":""}]},"oriental-bank":{"bank":"ORIENTAL BANK","country":"PR","branches":[{"bic":"OBPRPRSJ","bank":"ORIENTAL BANK","branch":"","city":"HATO REY","country":"PR","address":""}]},"ponce-federal-bank":{"bank":"PONCE FEDERAL BANK","country":"PR","branches":[{"bic":"PFEBPR21","bank":"PONCE FEDERAL BANK","branch":"","city":"PONCE","country":"PR","address":""}]},"scotiabank-de-puerto-rico":{"bank":"SCOTIABANK DE PUERTO RICO","country":"PR","branches":[{"bic":"NOSCPR22","bank":"SCOTIABANK DE PUERTO RICO","branch":"","city":"HATO REY","country":"PR","address":""},{"bic":"NOSCPR22MIA","bank":"SCOTIABANK DE PUERTO RICO","branch":"","city":"SAN JUAN","country":"PR","address":""}]},"statetrust-international-bank-and-trust-llc":{"bank":"STATETRUST INTERNATIONAL BANK AND TRUST, LLC","country":"PR","branches":[{"bic":"STULPRSJ","bank":"STATETRUST INTERNATIONAL BANK AND TRUST, LLC","branch":"","city":"SAN JUAN","country":"PR","address":""}]},"stern-international-bank-llc":{"bank":"STERN INTERNATIONAL BANK LLC","country":"PR","branches":[{"bic":"SIECPRSJ","bank":"STERN INTERNATIONAL BANK LLC","branch":"","city":"SAN JUAN","country":"PR","address":""}]},"vestin-bank-international-llc":{"bank":"VESTIN BANK INTERNATIONAL LLC","country":"PR","branches":[{"bic":"VEILPRSJ","bank":"VESTIN BANK INTERNATIONAL LLC","branch":"","city":"SAN JUAN","country":"PR","address":""}]}},"totalBranches":33}