{"countryCode":"UZ","branches":[{"bic":"ASACUZ22","bank":"ASIA ALLIANCE BANK","branch":"","city":"TASHKENT","country":"UZ","address":""},{"bic":"CBUZUZ22","bank":"CENTRAL BANK OF THE REPUBLIC UZBEKISTAN","branch":"","city":"TASHKENT","country":"UZ","address":""},{"bic":"CRIDUZ21","bank":"CREDIT-STANDARD BANK","branch":"","city":"TASHKENT","country":"UZ","address":""},{"bic":"HPCJUZ22","bank":"'HI-TECH BANK' PRIVATE CLOSED JOINT STOCK COMMERCIAL BANK","branch":"","city":"TASHKENT","country":"UZ","address":""},{"bic":"INFBUZ2X","bank":"INFINBANK","branch":"","city":"TASHKENT","country":"UZ","address":""},{"bic":"UZHOUZ22","bank":"IPOTEKA-BANK","branch":"","city":"TASHKENT","country":"UZ","address":""},{"bic":"PAKHUZ22","bank":"JOINT STOCK COMMERCIAL BANK 'AGROBANK'","branch":"","city":"TASHKENT","country":"UZ","address":""},{"bic":"JSCSUZ22","bank":"JOINT STOCK COMMERCIAL BANK SAVDOGAR","branch":"","city":"TASHKENT","country":"UZ","address":""},{"bic":"ASBKUZ22","bank":"JOINT-STOCK COMMERCIAL BANK ASAKA","branch":"","city":"TASHKENT","country":"UZ","address":""},{"bic":"TUROUZ21AND","bank":"JOINT-STOCK COMMERCIAL BANK TURONBANK","branch":"(ANDIJAN BRANCH)","city":"ANDIJAN","country":"UZ","address":""},{"bic":"TUROUZ21BUH","bank":"JOINT-STOCK COMMERCIAL BANK TURONBANK","branch":"(BUKHARA BRANCH)","city":"BUKHARA","country":"UZ","address":""},{"bic":"TUROUZ21FER","bank":"JOINT-STOCK COMMERCIAL BANK TURONBANK","branch":"(FERGANA BRANCH)","city":"FERGHANA","country":"UZ","address":""},{"bic":"TUROUZ21SYR","bank":"JOINT-STOCK COMMERCIAL BANK TURONBANK","branch":"(SYRDARYA BRANCH)","city":"GULISTAN","country":"UZ","address":""},{"bic":"TUROUZ21JIZ","bank":"JOINT-STOCK COMMERCIAL BANK TURONBANK","branch":"(JIZZAH BRANCH)","city":"JIZZAH","country":"UZ","address":""},{"bic":"TUROUZ21KAR","bank":"JOINT-STOCK COMMERCIAL BANK TURONBANK","branch":"(KARSHI BRANCH)","city":"KARSHI","country":"UZ","address":""},{"bic":"TUROUZ21NAM","bank":"JOINT-STOCK COMMERCIAL BANK TURONBANK","branch":"(NAMANGAN BRANCH)","city":"NAMANGAN","country":"UZ","address":""},{"bic":"TUROUZ21NAV","bank":"JOINT-STOCK COMMERCIAL BANK TURONBANK","branch":"(NAVOI BRANCH)","city":"NAVOI","country":"UZ","address":""},{"bic":"TUROUZ21NUK","bank":"JOINT-STOCK COMMERCIAL BANK TURONBANK","branch":"(NUKUS BRANCH)","city":"NUKUS","country":"UZ","address":""},{"bic":"TUROUZ21SAM","bank":"JOINT-STOCK COMMERCIAL BANK TURONBANK","branch":"(SAMARKAND BRANCH)","city":"SAMARKAND","country":"UZ","address":""},{"bic":"TUROUZ21SHK","bank":"JOINT-STOCK COMMERCIAL BANK TURONBANK","branch":"(SHAKHRISABZ BRANCH)","city":"SHAKHRISABZ","country":"UZ","address":""},{"bic":"TUROUZ21CHL","bank":"JOINT-STOCK COMMERCIAL BANK TURONBANK","branch":"(CHILANZAR BRANCH)","city":"TASHKENT","country":"UZ","address":""},{"bic":"TUROUZ21KHZ","bank":"JOINT-STOCK COMMERCIAL BANK TURONBANK","branch":"(KHAMZA BRANCH)","city":"TASHKENT","country":"UZ","address":""},{"bic":"TUROUZ21MIR","bank":"JOINT-STOCK COMMERCIAL BANK TURONBANK","branch":"(MIROBOD BRANCH)","city":"TASHKENT","country":"UZ","address":""},{"bic":"TUROUZ22","bank":"JOINT-STOCK COMMERCIAL BANK TURONBANK","branch":"","city":"TASHKENT","country":"UZ","address":""},{"bic":"TUROUZ21SUR","bank":"JOINT-STOCK COMMERCIAL BANK TURONBANK","branch":"(SURKHANDARYA BRANCH)","city":"TERMEZ","country":"UZ","address":""},{"bic":"TUROUZ21KHR","bank":"JOINT-STOCK COMMERCIAL BANK TURONBANK","branch":"(KHOREZM BRANCH)","city":"URGENCH","country":"UZ","address":""},{"bic":"TUROUZ21ZAN","bank":"JOINT-STOCK COMMERCIAL BANK TURONBANK","branch":"(ZANGIOTA BRANCH)","city":"ZANGIOTA","country":"UZ","address":""},{"bic":"SCPEUZ22","bank":"JOINT-STOCK COMMERCIAL XALQ BANK OF THE REPUBLIC OF UZBEKISTAN","branch":"","city":"TASHKENT","country":"UZ","address":""},{"bic":"JSCLUZ22","bank":"JSC ALOQABANK","branch":"","city":"TASHKENT","country":"UZ","address":""},{"bic":"INIPUZ21AND","bank":"JSIC BANK IPAK YULI","branch":"(ANDIJAN)","city":"ANDIJAN","country":"UZ","address":""},{"bic":"INIPUZ21QAR","bank":"JSIC BANK IPAK YULI","branch":"(KARSHI)","city":"KARSHI","country":"UZ","address":""},{"bic":"INIPUZ21NAM","bank":"JSIC BANK IPAK YULI","branch":"(NAMANGAN)","city":"NAMANGAN","country":"UZ","address":""},{"bic":"INIPUZ21NAV","bank":"JSIC BANK IPAK YULI","branch":"(NAVOI BRANCH)","city":"NAVOI","country":"UZ","address":""},{"bic":"INIPUZ21UMA","bank":"JSIC BANK IPAK YULI","branch":"(REGIONAL BRANCH 'UMAR')","city":"SAMARKAND","country":"UZ","address":""},{"bic":"INIPUZ21SHZ","bank":"JSIC BANK IPAK YULI","branch":"(SHAKHRISABZ)","city":"SHAKHRISABZ","country":"UZ","address":""},{"bic":"INIPUZ21CHL","bank":"JSIC BANK IPAK YULI","branch":"(CHILANZAR)","city":"TASHKENT","country":"UZ","address":""},{"bic":"INIPUZ21MRB","bank":"JSIC BANK IPAK YULI","branch":"(MIRABAD BRANCH)","city":"TASHKENT","country":"UZ","address":""},{"bic":"INIPUZ21MUB","bank":"JSIC BANK IPAK YULI","branch":"(MIRZO ULUGBEK BRANCH)","city":"TASHKENT","country":"UZ","address":""},{"bic":"INIPUZ21SGB","bank":"JSIC BANK IPAK YULI","branch":"(SAGBON)","city":"TASHKENT","country":"UZ","address":""},{"bic":"INIPUZ21SHB","bank":"JSIC BANK IPAK YULI","branch":"(SHAYHONTOHUR)","city":"TASHKENT","country":"UZ","address":""},{"bic":"INIPUZ21URB","bank":"JSIC BANK IPAK YULI","branch":"(URIKZOR BRANCH)","city":"TASHKENT","country":"UZ","address":""},{"bic":"INIPUZ21YKB","bank":"JSIC BANK IPAK YULI","branch":"(YAKKASARAY BRANCH)","city":"TASHKENT","country":"UZ","address":""},{"bic":"INIPUZ22","bank":"JSIC BANK IPAK YULI","branch":"","city":"TASHKENT","country":"UZ","address":""},{"bic":"INIPUZ21YNG","bank":"JSIC BANK IPAK YULI","branch":"(YANGIYUL')","city":"YANGIYUL","country":"UZ","address":""},{"bic":"KACHUZ22","bank":"KAPITALBANK, JSCB","branch":"","city":"TASHKENT","country":"UZ","address":""},{"bic":"KODBUZ22","bank":"KDB BANK UZBEKISTAN JSC","branch":"","city":"TASHKENT","country":"UZ","address":""},{"bic":"KHKKUZ22","bank":"KHAMKORBANK AKB","branch":"","city":"ANDIZHAN","country":"UZ","address":""},{"bic":"XKCEUZ31","bank":"KHOREZM INTERREGION COMMODITY EXCHANGE","branch":"","city":"TASHKENT","country":"UZ","address":""},{"bic":"MICDUZ22","bank":"MICROCREDITBANK","branch":"","city":"TASHKENT","country":"UZ","address":""},{"bic":"NBFAUZ2X","bank":"NATIONAL BANK FOR FOREIGN ECONOMIC ACTIVITY OF THE REPUBLIC OF UZBEKISTAN","branch":"","city":"TASHKENT","country":"UZ","address":""},{"bic":"OJMIUZ21","bank":"OJSC MICROCREDITBANK","branch":"","city":"TASHKENT","country":"UZ","address":""},{"bic":"ORFBUZ22","bank":"PJSCB 'ORIENT FINANCE'","branch":"","city":"TASHKENT","country":"UZ","address":""},{"bic":"TRKSUZ22","bank":"PJSCB TURKISTON","branch":"","city":"TASHKENT","country":"UZ","address":""},{"bic":"PJUNUZ22","bank":"PJSCB UNIVERSAL BANK","branch":"","city":"KOKAND","country":"UZ","address":""},{"bic":"DVRBUZ22","bank":"PRIVATE BANK 'DAVR BANK'","branch":"","city":"TASHKENT","country":"UZ","address":""},{"bic":"GJSOUZ22","bank":"'QISHLOQ QURILISH BANK' JOINT-STOCK COMMERCIAL BANK","branch":"","city":"TASHKENT","country":"UZ","address":""},{"bic":"RVBKUZ22","bank":"RAVNAQ BANK","branch":"","city":"TASHKENT","country":"UZ","address":""},{"bic":"TRSAUZ22","bank":"TRUSTBANK, PRIVATE JOINT STOCK-EXCHANGE BANK","branch":"","city":"TASHKENT","country":"UZ","address":""},{"bic":"POUNUZ21","bank":"UNIVERSAL BANK PRIVATE JOINT-STOCK COMMERCIAL BANK","branch":"","city":"KOKANY","country":"UZ","address":""},{"bic":"XUNIUZ21","bank":"UNIVERSAL BROKER'S EXCHANGE 'TASHKENT'","branch":"","city":"TASHKENT","country":"UZ","address":""},{"bic":"XCETUZ21","bank":"UNIVERSAL COMMODITY EXCHANGE 'TASHKENT'","branch":"","city":"TASHKENT","country":"UZ","address":""},{"bic":"UZTUUZ22","bank":"UT-BANK","branch":"","city":"TASHKENT","country":"UZ","address":""},{"bic":"UJSIUZ22","bank":"'UZBEK INDUSTRIAL AND CONSTRUCTION BANK' JOINT-STOCK COMMERCIAL BANK","branch":"","city":"TASHKENT","country":"UZ","address":""},{"bic":"XCUEUZ21","bank":"UZBEKISTAN REPUBLICAN CURRENCY EXCHANGE, THE","branch":"","city":"TASHKENT","country":"UZ","address":""},{"bic":"XSTEUZ21","bank":"UZBEKISTAN STOCK EXCHANGE","branch":"","city":"TASHKENT","country":"UZ","address":""}]}