{"countryCode":"BI","banks":[{"name":"BANQUE BURUNDAISE POUR LE COMMERCE ET L'INVESTISSEMENT","slug":"banque-burundaise-pour-le-commerce-et-l-investissement","primaryBic":"BUCIBIBI"},{"name":"BANQUE COMMERCIALE DU BURUNDI","slug":"banque-commerciale-du-burundi","primaryBic":"BCBUBIBI"},{"name":"BANQUE DE CREDIT DE BUJUMBURA","slug":"banque-de-credit-de-bujumbura","primaryBic":"BCRBBIBI"},{"name":"BANQUE DE GESTION ET DE FINANCEMENT","slug":"banque-de-gestion-et-de-financement","primaryBic":"BKGFBIBI"},{"name":"BANQUE DE LA REPUBLIQUE DU BURUNDI","slug":"banque-de-la-republique-du-burundi","primaryBic":"BRBUBIB2"},{"name":"CAISSE CENTRALE DE MOBILISATION ET DE FINANCEMENT","slug":"caisse-centrale-de-mobilisation-et-de-financement","primaryBic":"CCMFBIB1"},{"name":"CAISSE D'EPARGNE DU BURUNDI","slug":"caisse-d-epargne-du-burundi","primaryBic":"CADBBIB1"},{"name":"CENTRAL BANK OF BURUNDI","slug":"central-bank-of-burundi","primaryBic":"CBBBBIB1"},{"name":"CRDB BANK BURUNDI S.A","slug":"crdb-bank-burundi-s-a","primaryBic":"CORUBIBU"},{"name":"DIAMOND TRUST BANK BURUNDI S.A","slug":"diamond-trust-bank-burundi-s-a","primaryBic":"DTKEBIBI"},{"name":"ECOBANK BURUNDI","slug":"ecobank-burundi","primaryBic":"ECOCBIBI"},{"name":"FINBANK","slug":"finbank","primaryBic":"FIKNBIBI"},{"name":"INTERBANK BURUNDI","slug":"interbank-burundi","primaryBic":"IBBUBIBIADI"},{"name":"KCB BANK BURUNDI LIMITED","slug":"kcb-bank-burundi-limited","primaryBic":"KCBLBIBI"},{"name":"MERIDIEN BIAO BANK BURUNDI SARL","slug":"meridien-biao-bank-burundi-sarl","primaryBic":"MBBSBIB1"}],"bankDetails":{"banque-burundaise-pour-le-commerce-et-l-investissement":{"bank":"BANQUE BURUNDAISE POUR LE COMMERCE ET L'INVESTISSEMENT","country":"BI","branches":[{"bic":"BUCIBIBI","bank":"BANQUE BURUNDAISE POUR LE COMMERCE ET L'INVESTISSEMENT","branch":"","city":"BUJUMBURA","country":"BI","address":""}]},"banque-commerciale-du-burundi":{"bank":"BANQUE COMMERCIALE DU BURUNDI","country":"BI","branches":[{"bic":"BCBUBIBI","bank":"BANQUE COMMERCIALE DU BURUNDI","branch":"","city":"BUJUMBURA","country":"BI","address":""}]},"banque-de-credit-de-bujumbura":{"bank":"BANQUE DE CREDIT DE BUJUMBURA","country":"BI","branches":[{"bic":"BCRBBIBI","bank":"BANQUE DE CREDIT DE BUJUMBURA","branch":"","city":"BUJUMBURA","country":"BI","address":""}]},"banque-de-gestion-et-de-financement":{"bank":"BANQUE DE GESTION ET DE FINANCEMENT","country":"BI","branches":[{"bic":"BKGFBIBI","bank":"BANQUE DE GESTION ET DE FINANCEMENT","branch":"","city":"BUJUMBURA","country":"BI","address":""}]},"banque-de-la-republique-du-burundi":{"bank":"BANQUE DE LA REPUBLIQUE DU BURUNDI","country":"BI","branches":[{"bic":"BRBUBIB2","bank":"BANQUE DE LA REPUBLIQUE DU BURUNDI","branch":"","city":"BUJUMBURA","country":"BI","address":""},{"bic":"BRBUBIBI","bank":"BANQUE DE LA REPUBLIQUE DU BURUNDI","branch":"","city":"BUJUMBURA","country":"BI","address":""}]},"caisse-centrale-de-mobilisation-et-de-financement":{"bank":"CAISSE CENTRALE DE MOBILISATION ET DE FINANCEMENT","country":"BI","branches":[{"bic":"CCMFBIB1","bank":"CAISSE CENTRALE DE MOBILISATION ET DE FINANCEMENT","branch":"","city":"BUJUMBURA","country":"BI","address":""}]},"caisse-d-epargne-du-burundi":{"bank":"CAISSE D'EPARGNE DU BURUNDI","country":"BI","branches":[{"bic":"CADBBIB1","bank":"CAISSE D'EPARGNE DU BURUNDI","branch":"","city":"BUJUMBURA","country":"BI","address":""}]},"central-bank-of-burundi":{"bank":"CENTRAL BANK OF BURUNDI","country":"BI","branches":[{"bic":"CBBBBIB1","bank":"CENTRAL BANK OF BURUNDI","branch":"","city":"BUJUMBURA","country":"BI","address":""}]},"crdb-bank-burundi-s-a":{"bank":"CRDB BANK BURUNDI S.A","country":"BI","branches":[{"bic":"CORUBIBU","bank":"CRDB BANK BURUNDI S.A","branch":"","city":"BUJUMBURA","country":"BI","address":""}]},"diamond-trust-bank-burundi-s-a":{"bank":"DIAMOND TRUST BANK BURUNDI S.A","country":"BI","branches":[{"bic":"DTKEBIBI","bank":"DIAMOND TRUST BANK BURUNDI S.A","branch":"","city":"BUJUMBURA","country":"BI","address":""}]},"ecobank-burundi":{"bank":"ECOBANK BURUNDI","country":"BI","branches":[{"bic":"ECOCBIBI","bank":"ECOBANK BURUNDI","branch":"","city":"BUJUMBURA","country":"BI","address":""}]},"finbank":{"bank":"FINBANK","country":"BI","branches":[{"bic":"FIKNBIBI","bank":"FINBANK","branch":"","city":"BUJUMBURA","country":"BI","address":""}]},"interbank-burundi":{"bank":"INTERBANK BURUNDI","country":"BI","branches":[{"bic":"IBBUBIBIADI","bank":"INTERBANK BURUNDI","branch":"(AVENUE DE L'INDUSTRIE BRANCH)","city":"BUJUMBURA","country":"BI","address":""},{"bic":"IBBUBIBI","bank":"INTERBANK BURUNDI","branch":"","city":"BUJUMBURA","country":"BI","address":""}]},"kcb-bank-burundi-limited":{"bank":"KCB BANK BURUNDI LIMITED","country":"BI","branches":[{"bic":"KCBLBIBI","bank":"KCB BANK BURUNDI LIMITED","branch":"","city":"BUJUMBURA","country":"BI","address":""}]},"meridien-biao-bank-burundi-sarl":{"bank":"MERIDIEN BIAO BANK BURUNDI SARL","country":"BI","branches":[{"bic":"MBBSBIB1","bank":"MERIDIEN BIAO BANK BURUNDI SARL","branch":"","city":"BUJUMBURA","country":"BI","address":""}]}},"totalBranches":17}